spotify_cli_client/__init__.py
spotify_cli_client/cli.py
spotify_cli_client/spotifyCLI.py
spotify_cli_client/spotifyClient.py
spotify_cli_client-0.1.0.dist-info/licenses/LICENSE
spotify_cli_client-0.1.0.dist-info/METADATA
spotify_cli_client-0.1.0.dist-info/WHEEL
spotify_cli_client-0.1.0.dist-info/entry_points.txt
spotify_cli_client-0.1.0.dist-info/top_level.txt
spotify_cli_client-0.1.0.dist-info/RECORD
