Metadata-Version: 2.4
Name: spotify-cli-client
Version: 0.1.0
Summary: Simple Spotify Client
Author: Sudharshan V
Author-email: sudarshan61kv@gmail.com
License: MIT
Classifier: Programming Language :: Python :: 3
Classifier: Operating System :: OS Independent
Requires-Python: >=3.6
License-File: LICENSE
Requires-Dist: click
Requires-Dist: spotipy
Requires-Dist: InquirerPy
Dynamic: author
Dynamic: author-email
Dynamic: classifier
Dynamic: description
Dynamic: description-content-type
Dynamic: license
Dynamic: license-file
Dynamic: requires-dist
Dynamic: requires-python
Dynamic: summary
